fastapi_module_loader/__init__.py
fastapi_module_loader/exceptions.py
fastapi_module_loader/loader.py
fastapi_module_loader/module.py
fastapi_module_loader/py.typed
fastapi_module_loader-0.4.1.dist-info/licenses/LICENSE
fastapi_module_loader-0.4.1.dist-info/WHEEL
fastapi_module_loader-0.4.1.dist-info/METADATA
fastapi_module_loader-0.4.1.dist-info/RECORD
