Metadata-Version: 2.4
Name: fastapi-module-loader
Version: 0.4.1
Summary: FastAPI modules loading for better structure in your projects (like Django AppConfig)
Author: TEAM23 GmbH
Author-email: TEAM23 GmbH <info@team23.de>
License-Expression: MIT
License-File: LICENSE
Requires-Dist: fastapi>=0.100.0,<1.0.0
Requires-Python: >=3.10
Project-URL: Repository, https://github.com/team23/fastapi-module-loading
